README.md
setup.cfg
setup.py
./fq-checkpair
./fq-repair
./fq-trim
./fq-zwc
fqutil/__init__.py
fqutil/fastq.py
fqutil/util.py
fqutil.egg-info/PKG-INFO
fqutil.egg-info/SOURCES.txt
fqutil.egg-info/dependency_links.txt
fqutil.egg-info/not-zip-safe
fqutil.egg-info/top_level.txt