Metadata-Version: 1.0
Name: fqutil
Version: 1.1
Summary: Several useful tools for manipulating FASTQ files.
Home-page: https://github.com/jstaf/fqutil
Author: Jeff Stafford
Author-email: jeff.stafford@queensu.ca
License: BSD-3
Platform: UNKNOWN
